{
	"verbosity": 0,
	"base_transmission_risk": 0.27675,
	"subclinical_modifier": 0.6,
	"exposure_duration": [
		4.31,
		3.05
	],
	"time_until_symptoms": [
		1.49,
		1.75
	],
	"infection_duration": [
		10.65,
		4.15
	],
	"infection_risk_contact_type_weights": {
		"very_far": 0,
		"far": 0.26,
		"intermediate": 0.26,
		"close": 1
	},
	"age_transmission_discount": {
		"slope": 0,
		"intercept": 1
	},
	"age_symptom_discount": {
		"slope": 0,
		"intercept": 0.6
	},
	"mask_filter_efficiency": {
		"exhale": 0.5,
		"inhale": 0.7
	}
}
